{"extension":{"type":"Extension","plural":true},"modifierExtension":{"type":"Extension","plural":true},"name":{"type":"CodeableConcept","plural":false},"text":{"type":"string","plural":false},"answerDecimal":{"type":"decimal","plural":false},"answerInteger":{"type":"integer","plural":false},"answerBoolean":{"type":"boolean","plural":false},"answerDate":{"type":"date","plural":false},"answerString":{"type":"string","plural":false},"answerDateTime":{"type":"dateTime","plural":false},"answerInstant":{"type":"instant","plural":false},"choice":{"type":"Coding","plural":true},"options":{"type":"ResourceReference","plural":false},"dataBoolean":{"type":"boolean","plural":false},"dataInteger":{"type":"integer","plural":false},"dataDecimal":{"type":"decimal","plural":false},"dataBase64Binary":{"type":"base64Binary","plural":false},"dataInstant":{"type":"instant","plural":false},"dataString":{"type":"string","plural":false},"dataUri":{"type":"uri","plural":false},"dataDate":{"type":"date","plural":false},"dataDateTime":{"type":"dateTime","plural":false},"dataCode":{"type":"code","plural":false},"dataOid":{"type":"oid","plural":false},"dataUuid":{"type":"uuid","plural":false},"dataId":{"type":"id","plural":false},"dataAttachment":{"type":"Attachment","plural":false},"dataIdentifier":{"type":"Identifier","plural":false},"dataCodeableConcept":{"type":"CodeableConcept","plural":false},"dataCoding":{"type":"Coding","plural":false},"dataQuantity":{"type":"Quantity","plural":false},"dataRange":{"type":"Range","plural":false},"dataPeriod":{"type":"Period","plural":false},"dataRatio":{"type":"Ratio","plural":false},"dataResource":{"type":"ResourceReference","plural":false},"dataSampledData":{"type":"SampledData","plural":false},"dataHumanName":{"type":"HumanName","plural":false},"dataAddress":{"type":"Address","plural":false},"dataContact":{"type":"Contact","plural":false},"dataSchedule":{"type":"Schedule","plural":false},"remarks":{"type":"string","plural":false},"group":{"type":"Questionnaire.Group","plural":true}}